zensols/db/resources/sqlite-stash.sql
zensols/db/__init__.py
zensols/db/bean.py
zensols/db/conn.py
zensols/db/connpool.py
zensols/db/dataclass.py
zensols/db/parse.py
zensols/db/sqlite.py
zensols/db/stash.py
zensols_db-1.5.0.dist-info/METADATA
zensols_db-1.5.0.dist-info/WHEEL
zensols_db-1.5.0.dist-info/licenses/LICENSE.md
zensols_db-1.5.0.dist-info/RECORD
