Metadata-Version: 2.3
Name: zensols_db
Version: 1.5.0
Summary: A library of database convenience utilities, typically for creation of temporary files for processing large data.
Project-URL: Homepage, https://github.com/plandes/db
Project-URL: Documentation, https://plandes.github.io/db
Project-URL: Repository, https://github.com/plandes/db.git
Project-URL: Issues, https://github.com/plandes/db/issues
Project-URL: Changelog, https://github.com/plandes/db/blob/master/CHANGELOG.md
Author-email: Paul Landes <landes@mailc.net>
License: MIT
Keywords: database,sqlite
Requires-Python: <3.15,>=3.11
Requires-Dist: jsonpickle~=3.2.2
Requires-Dist: pandas~=2.3.0
Requires-Dist: zensols-util~=1.16.2
